deartriogui/__init__.py
deartriogui/_runners.py
deartriogui/_version.py
deartriogui/_tests/__init__.py
deartriogui/_tests/conftest.py
deartriogui-0.0.2.dist-info/LICENSE
deartriogui-0.0.2.dist-info/LICENSE.APACHE2
deartriogui-0.0.2.dist-info/LICENSE.MIT
deartriogui-0.0.2.dist-info/METADATA
deartriogui-0.0.2.dist-info/WHEEL
deartriogui-0.0.2.dist-info/top_level.txt
deartriogui-0.0.2.dist-info/RECORD
